.gitignore
.gitmodules
LICENSE
README.md
pyproject.toml
setup.cfg
setup.py
.github/workflows/CI.yml
.github/workflows/release.yml
realsr_ncnn_vulkan_python/CMakeLists.txt
realsr_ncnn_vulkan_python/realsr.i
realsr_ncnn_vulkan_python/realsr_ncnn_vulkan.py
realsr_ncnn_vulkan_python/realsr_wrapped.cpp
realsr_ncnn_vulkan_python/realsr_wrapped.h
realsr_ncnn_vulkan_python.egg-info/PKG-INFO
realsr_ncnn_vulkan_python.egg-info/SOURCES.txt
realsr_ncnn_vulkan_python.egg-info/dependency_links.txt
realsr_ncnn_vulkan_python.egg-info/requires.txt
realsr_ncnn_vulkan_python.egg-info/top_level.txt