Metadata-Version: 2.1
Name: realsr-ncnn-vulkan-python
Version: 1.0.0
Summary: A Python FFI of nihui/realsr-ncnn-vulkan achieved with SWIG
Home-page: https://github.com/media2x/realsr-ncnn-vulkan-python
Author: ArchieMeng
Author-email: archiemeng@protonmail.com
Maintainer: K4YT3X
Maintainer-email: k4yt3x@k4yt3x.com
License: MIT
Keywords: realsr,ncnn,vulkan,swig
Platform: any
Classifier: Environment :: Console
Classifier: Programming Language :: Python
Classifier: Programming Language :: Python :: 3
Classifier: Operating System :: OS Independent
Requires-Python: >=3.6
License-File: LICENSE
